watercrawl_plugin/__init__.py
watercrawl_plugin/base.py
watercrawl_plugin/pipeline.py
wattercrawl_plugin-0.0.1.dist-info/LICENSE
wattercrawl_plugin-0.0.1.dist-info/METADATA
wattercrawl_plugin-0.0.1.dist-info/WHEEL
wattercrawl_plugin-0.0.1.dist-info/top_level.txt
wattercrawl_plugin-0.0.1.dist-info/RECORD
