Metadata-Version: 2.1
Name: wattercrawl-plugin
Version: 0.0.1
Summary: This project used for writing wattercrawl plugin for scrapy
Author-email: AmirMohsen Asaran <info@wattercrawl.ai>
Project-URL: Homepage, https://github.com/wattercrawl/wattercrawl-plugin
Project-URL: Issues, https://github.com/wattercrawl/wattercrawl/issues
Classifier: Programming Language :: Python :: 3
Classifier: License :: OSI Approved :: MIT License
Classifier: Operating System :: OS Independent
Requires-Python: >=3.11
License-File: LICENSE
